{
  "HP_timestamp": {
    "name": "${HP_timestamp}",
    "format": "",
    "group": "HeaterPlus",
    "description": "Current Timestamp",
    "type": "string",
    "source": "heater_plus",
    "value": "2026-02-17T17:33:25"
  },
  "HP_temperature_set": {
    "name": "${HP_temperature_set}",
    "format": "{deg}",
    "group": "HeaterPlus",
    "description": "Temperature Setpoint",
    "type": "string",
    "source": "heater_plus",
    "value": 20.0
  },
  "HP_temperature_dome": {
    "name": "${HP_temperature_dome}",
    "format": "{deg}",
    "group": "HeaterPlus",
    "description": "Temperature Dome",
    "type": "string",
    "source": "heater_plus",
    "value": 23.6
  },
  "HP_dewpoint_dome": {
    "name": "${HP_dewpoint_dome}",
    "format": "{deg}",
    "group": "HeaterPlus",
    "description": "Dewpoint Dome",
    "type": "string",
    "source": "heater_plus",
    "value": -10.9
  },
  "HP_humidity_dome": {
    "name": "${HP_humidity_dome}",
    "format": "",
    "group": "HeaterPlus",
    "description": "Humidity Dome",
    "type": "humidity",
    "source": "heater_plus",
    "value": 9.2
  },
  "HP_heater_duty": {
    "name": "${HP_heater_duty}",
    "format": "",
    "group": "HeaterPlus",
    "description": "Heater duty cycle",
    "type": "duty",
    "source": "heater_plus",
    "value": 0.0
  },
  "HP_fan_duty": {
    "name": "${HP_fan_duty}",
    "format": "",
    "group": "HeaterPlus",
    "description": "Fan duty cycle",
    "type": "duty",
    "source": "heater_plus",
    "value": 100.0
  },
  "HP_light_lux": {
    "name": "${HP_light_lux}",
    "format": "",
    "group": "HeaterPlus",
    "description": "Lux",
    "type": "light",
    "source": "heater_plus",
    "value": 184.2
  },
  "HP_ina_vbus": {
    "name": "${HP_ina_vbus}",
    "format": "",
    "group": "HeaterPlus",
    "description": "Supply voltage (INA226)",
    "type": "voltage",
    "source": "heater_plus",
    "value": 12.084
  },
  "HP_ina_power": {
    "name": "${HP_ina_power}",
    "format": "",
    "group": "HeaterPlus",
    "description": "Supply power total (INA226: heater + fan + board)",
    "type": "power",
    "source": "heater_plus",
    "value": 0.48
  }
}